Workbook

Sheet Cover
B3: BOBWEIR PHARMACEUTICALS, INC.
B5: Integrated Financial Model
B8: Model Overview
B10: Company Description: | C10: Specialty pharmaceutical company focused on rare diseases and oncology
B11: Headquarters: | C11: San Francisco, CA
B12: Founded: | C12: 2008
B13: Employees: | C13: 2850
B15: Model Details
B17: Historical Period: | C17: 2021A - 2023A
B18: Projection Period: | C18: 2024E - 2028E
B19: Last Updated: | C19: January 2024
B21: Product Portfolio
B23: Product | C23: Indication | D23: 2023 Revenue | E23: Launch Year
B24: Neurex | C24: Rare neurological disorder | D24: $850M | E24: 2019
B25: Oncovir | C25: Solid tumor oncology | D25: $720M | E25: 2020
B26: Hemaguard | C26: Rare blood disorder | D26: $540M | E26: 2018
B27: Cardioshield | C27: Cardiovascular | D27: $420M | E27: 2021
B28: Dermaclear | C28: Dermatology | D28: $310M | E28: 2022
B29: Respiron | C29: Respiratory | D29: $160M | E29: 2023

Sheet Assumptions
B2: Assumption | C2: Units | D2: 2021A | E2: 2022A | F2: 2023A | G2: 2024E | H2: 2025E | I2: 2026E | J2: 2027E | K2: 2028E
B4: REVENUE ASSUMPTIONS
B5: Neurex Growth Rate | C5: % | D5: 0.15 | E5: 0.12 | F5: 0.08 | G5: 0.06 | H5: 0.04 | I5: 0.03 | J5: 0.02 | K5: 0.01
B6: Oncovir Growth Rate | C6: % | D6: 0.25 | E6: 0.22 | F6: 0.18 | G6: 0.15 | H6: 0.12 | I6: 0.1 | J6: 0.08 | K6: 0.06
B7: Hemaguard Growth Rate | C7: % | D7: 0.1 | E7: 0.08 | F7: 0.05 | G7: 0.03 | H7: 0.02 | I7: 0.01 | J7: 0 | K7: -0.02
B8: Cardioshield Growth Rate | C8: % | E8: 0.8 | F8: 0.35 | G8: 0.25 | H8: 0.18 | I8: 0.12 | J8: 0.08 | K8: 0.05
B9: Dermaclear Growth Rate | C9: % | F9: 1.5 | G9: 0.4 | H9: 0.3 | I9: 0.22 | J9: 0.15 | K9: 0.1
B10: Respiron Growth Rate | C10: % | G10: 0.6 | H10: 0.45 | I10: 0.35 | J10: 0.25 | K10: 0.18
B12: MARGIN ASSUMPTIONS
B13: Gross Margin | C13: % | D13: 0.72 | E13: 0.73 | F13: 0.74 | G13: 0.745 | H13: 0.75 | I13: 0.755 | J13: 0.76 | K13: 0.765
B14: R&D % of Revenue | C14: % | D14: 0.18 | E14: 0.17 | F14: 0.16 | G14: 0.155 | H14: 0.15 | I14: 0.145 | J14: 0.14 | K14: 0.135
B15: SG&A % of Revenue | C15: % | D15: 0.28 | E15: 0.27 | F15: 0.26 | G15: 0.25 | H15: 0.24 | I15: 0.23 | J15: 0.22 | K15: 0.21
B16: D&A % of Revenue | C16: % | D16: 0.04 | E16: 0.04 | F16: 0.04 | G16: 0.04 | H16: 0.04 | I16: 0.04 | J16: 0.04 | K16: 0.04
B19: BALANCE SHEET ASSUMPTIONS
B20: Days Sales Outstanding | C20: days | D20: 55 | E20: 52 | F20: 50 | G20: 48 | H20: 46 | I20: 45 | J20: 44 | K20: 43
B21: Days Inventory | C21: days | D21: 90 | E21: 88 | F21: 85 | G21: 82 | H21: 80 | I21: 78 | J21: 76 | K21: 75
B22: Days Payable | C22: days | D22: 45 | E22: 48 | F22: 50 | G22: 52 | H22: 54 | I22: 55 | J22: 56 | K22: 57
B23: CapEx % of Revenue | C23: % | D23: 0.05 | E23: 0.05 | F23: 0.05 | G23: 0.045 | H23: 0.045 | I23: 0.04 | J23: 0.04 | K23: 0.04
B26: TAX & OTHER
B27: Effective Tax Rate | C27: % | D27: 0.21 | E27: 0.21 | F27: 0.21 | G27: 0.21 | H27: 0.21 | I27: 0.21 | J27: 0.21 | K27: 0.21

Sheet Revenue
D2: 2021A | E2: 2022A | F2: 2023A | G2: 2024E | H2: 2025E | I2: 2026E | J2: 2027E | K2: 2028E
B4: PRODUCT REVENUE ($M)
B5: Neurex | D5: 650 | E5: 728 | F5: 786 | G5: =F5*(1+Assumptions!G5) | H5: 866 | I5: =H5*(1+Assumptions!I5) | J5: =I5*(1+Assumptions!J5) | K5: =J5*(1+Assumptions!K5)
B6: Oncovir | D6: 380 | E6: 475 | F6: 561 | G6: =F6*(1+Assumptions!G6) | H6: =G6*(1+Assumptions!H6) | I6: =H6*(1+Assumptions!I6) | J6: =I6*(1+Assumptions!J6) | K6: =J6*(1+Assumptions!K6)
B7: Hemaguard | D7: 480 | E7: 518 | F7: 544 | G7: =F7*(1+Assumptions!G7) | H7: =G7*(1+Assumptions!H7) | I7: =H7*(1+Assumptions!I7) | J7: =I7*(1+Assumptions!J7) | K7: =J7*(1+Assumptions!K7)
B8: Cardioshield | D8: 180 | E8: 324 | F8: 437 | G8: =F8*(1+Assumptions!G8) | H8: =G8*(1+Assumptions!H8) | I8: =H8*(1+Assumptions!I8) | J8: =I8*(1+Assumptions!J8) | K8: =J8*(1+Assumptions!K8)
B9: Dermaclear | D9: 0 | E9: 85 | F9: 212 | G9: =F9*(1+Assumptions!G9) | H9: =G9*(1+Assumptions!H9) | I9: =H9*(1+Assumptions!I9) | J9: =I9*(1+Assumptions!J9) | K9: =J9*(1+Assumptions!K9)
B10: Respiron | D10: 0 | E10: 0 | F10: 160 | G10: =F10*(1+Assumptions!G10) | H10: =G10*(1+Assumptions!H10) | I10: =H10*(1+Assumptions!I10) | J10: =I10*(1+Assumptions!J10) | K10: =J10*(1+Assumptions!K10)
B12: Total Revenue | D12: =SUM(D5:D10) | E12: =SUM(E5:E10) | F12: =SUM(F5:F10) | G12: =SUM(G5:G10) | H12: =SUM(H5:H10) | I12: =SUM(I5:I10) | J12: =SUM(J5:J10) | K12: =SUM(K5:K10)
B14: YoY Growth % | D14: N/A | E14: =E12/D12-1 | F14: =F12/E12-1 | G14: =G12/F12-1 | H14: =H12/G12-1 | I14: =I12/H12-1 | J14: =J12/I12-1 | K14: =K12/J12-1

Sheet IS
D2: 2021A | E2: 2022A | F2: 2023A | G2: 2024E | H2: 2025E | I2: 2026E | J2: 2027E | K2: 2028E
B4: INCOME STATEMENT ($M)
B6: Revenue | D6: =Revenue!D12 | E6: =Revenue!E12 | F6: =Revenue!F12 | G6: =Revenue!G12 | H6: =Revenue!H12 | I6: =Revenue!I12 | J6: =Revenue!J12 | K6: =Revenue!K12
B7: Cost of Goods Sold | D7: =-D6*(1-Assumptions!D13) | E7: =-E6*(1-Assumptions!E13) | F7: =-F6*(1-Assumptions!F13) | G7: =-G6*(1-Assumptions!G13) | H7: =-H6*(1-Assumptions!H13) | I7: =-I6*(1-Assumptions!I13) | J7: =-J6*(1-Assumptions!J13) | K7: =-K6*(1-Assumptions!K13)
B8: Gross Profit | D8: =D6+D7 | E8: =E6+E7 | F8: =F6+F7 | G8: =G6+G7 | H8: =H6+H7 | I8: =I6+I7 | J8: =J6+J7 | K8: =K6+K7
B10: R&D Expense | D10: =-D6*Assumptions!D14 | E10: =-E6*Assumptions!E14 | F10: =-F6*Assumptions!F14 | G10: =-G6*Assumptions!G14 | H10: =-H6*Assumptions!H14 | I10: =-I6*Assumptions!I14 | J10: =-J6*Assumptions!J14 | K10: =-K6*Assumptions!K14
B11: SG&A Expense | D11: =-D6*Assumptions!D15 | E11: =-E6*Assumptions!E15 | F11: =-F6*Assumptions!F15 | G11: =-G6*Assumptions!G15 | H11: =-H6*Assumptions!H15 | I11: =-I6*Assumptions!I15 | J11: =-J6*Assumptions!J15 | K11: =-K6*Assumptions!K15
B12: D&A Expense | D12: =-D6*Assumptions!D16 | E12: =-E6*Assumptions!E16 | F12: =-F6*Assumptions!F16 | G12: =-G6*Assumptions!G16 | H12: =-H6*Assumptions!H16 | I12: =-I6*Assumptions!I16 | J12: =-J6*Assumptions!J16 | K12: =-K6*Assumptions!K16
B13: Operating Income (EBIT) | D13: =D8+D10+D11+D12 | E13: =E8+E10+E11+E12 | F13: =F8+F10+F11+F12 | G13: =G8+G10+G11+G12 | H13: =H8+H10+H11+H12 | I13: =I8+I10+I11+I12 | J13: =J8+J10+J11+J12 | K13: =K8+K10+K11+K12
B15: Interest Expense | D15: -45 | E15: -42 | F15: -40 | G15: -38 | H15: -36 | I15: -34 | J15: -32 | K15: -30
B16: Interest Income | D16: 5 | E16: 8 | F16: 12 | G16: 15 | H16: 18 | I16: 22 | J16: 26 | K16: 30
B17: Pre-Tax Income | D17: =D13+D15+D16 | E17: =E13+E15+E16 | F17: =F13+F15+F16 | G17: =G13+G15+G16 | H17: =H13+H15+H16 | I17: =I13+I15+I16 | J17: =J13+J15+J16 | K17: =K13+K15+K16
B19: Income Tax Expense | D19: =-D17*Assumptions!D27 | E19: =-E17*Assumptions!E27 | F19: =-F17*Assumptions!F27 | G19: =-G17*Assumptions!G27 | H19: =-H17*Assumptions!H27 | I19: =-I17*Assumptions!I27 | J19: =-J17*Assumptions!J27 | K19: =-K17*Assumptions!K27
B20: Net Income | D20: =D17+D19 | E20: =E17+E19 | F20: =F17+F19 | G20: =G17+G19 | H20: =H17+H19 | I20: =I17+I19 | J20: =J17+J19 | K20: =K17+K19
B22: MARGINS
B23: Gross Margin | D23: =D8/D6 | E23: =E8/E6 | F23: =F8/F6 | G23: =G8/G6 | H23: =H8/H6 | I23: =I8/I6 | J23: =J8/J6 | K23: =K8/K6
B24: R&D Margin | D24: =-D10/D6 | E24: =-E10/E6 | F24: =-F10/F6 | G24: =-G10/G6 | H24: =-H10/H6 | I24: =-I10/I6 | J24: =-J10/J6 | K24: =-K10/K6
B25: SG&A Margin | D25: =-D11/D6 | E25: =-E11/E6 | F25: =-F11/F6 | G25: =-G11/G6 | H25: =-H11/H6 | I25: =-I11/I6 | J25: =-J11/J6 | K25: =-K11/K6
B26: Operating Margin | D26: =D13/D6 | E26: =E13/E6 | F26: =F13/F6 | G26: =G13/G6 | H26: =H13/H6 | I26: =I13/I6 | J26: =J13/J6 | K26: =K13/K6
B27: Net Margin | D27: =D20/D6 | E27: =E20/E6 | F27: =F20/F6 | G27: =G20/G6 | H27: =H20/H6 | I27: =I20/I6 | J27: =J20/J6 | K27: =K20/K6

Sheet BS
D2: 2021A | E2: 2022A | F2: 2023A | G2: 2024E | H2: 2025E | I2: 2026E | J2: 2027E | K2: 2028E
B4: BALANCE SHEET ($M)
B6: ASSETS
B7: Cash & Equivalents | D7: 450 | E7: 580 | F7: 720 | G7: =F7+CF!G28 | H7: =G7+CF!H28 | I7: =H7+CF!I28 | J7: =I7+CF!J28 | K7: =J7+CF!K28
B8: Accounts Receivable | D8: 260 | E8: 295 | F8: 342 | G8: =Revenue!G12*Assumptions!G20/365 | H8: =Revenue!H12*Assumptions!H20/365 | I8: =Revenue!I12*Assumptions!I20/365 | J8: =Revenue!J12*Assumptions!J20/365 | K8: =Revenue!K12*Assumptions!K20/365
B9: Inventory | D9: 380 | E9: 420 | F9: 465 | G9: =-IS!G7*Assumptions!G21/365 | H9: =-IS!H7*Assumptions!H21/365 | I9: =-IS!I7*Assumptions!I21/365 | J9: =-IS!J7*Assumptions!J21/365 | K9: =-IS!K7*Assumptions!K21/365
B10: Other Current Assets | D10: 50 | E10: 55 | F10: 60 | G10: 65 | H10: 70 | I10: 75 | J10: 80 | K10: 85
B11: Total Current Assets | D11: =SUM(D7:D10) | E11: =SUM(E7:E10) | F11: =SUM(F7:F10) | G11: =SUM(G7:G10) | H11: =SUM(H7:H10) | I11: =SUM(I7:I10) | J11: =SUM(J7:J10) | K11: =SUM(K7:K10)
B13: PP&E, Net | D13: 320 | E13: 350 | F13: 385 | G13: =F13+Revenue!G12*Assumptions!G23+IS!G12 | H13: =G13+Revenue!H12*Assumptions!H23+IS!H12 | I13: =H13+Revenue!I12*Assumptions!I23+IS!I12 | J13: =I13+Revenue!J12*Assumptions!J23+IS!J12 | K13: =J13+Revenue!K12*Assumptions!K23+IS!K12
B14: Intangible Assets | D14: 850 | E14: 820 | F14: 790 | G14: 760 | H14: 730 | I14: 700 | J14: 670 | K14: 640
B15: Goodwill | D15: 420 | E15: 420 | F15: 420 | G15: 420 | H15: 420 | I15: 420 | J15: 420 | K15: 420
B16: Total Non-Current Assets | D16: =SUM(D13:D15) | E16: =SUM(E13:E15) | F16: =SUM(F13:F15) | G16: =SUM(G13:G15) | H16: =SUM(H13:H15) | I16: =SUM(I13:I15) | J16: =SUM(J13:J15) | K16: =SUM(K13:K15)
B18: TOTAL ASSETS | D18: =D11+D16 | E18: =E11+E16 | F18: =F11+F16 | G18: =G11+G16 | H18: =H11+H16 | I18: =I11+I16 | J18: =J11+J16 | K18: =K11+K16
B20: LIABILITIES
B21: Accounts Payable | D21: 170 | E21: 195 | F21: 220 | G21: =-IS!G7*Assumptions!G22/365 | H21: =-IS!H7*Assumptions!H22/365 | I21: =-IS!I7*Assumptions!I22/365 | J21: =-IS!J7*Assumptions!J22/365 | K21: =-IS!K7*Assumptions!K22/365
B22: Accrued Expenses | D22: 120 | E22: 130 | F22: 140 | G22: 150 | H22: 160 | I22: 170 | J22: 180 | K22: 190
B23: Total Current Liabilities | D23: =SUM(D21:D22) | E23: =SUM(E21:E22) | F23: =SUM(F21:F22) | G23: =SUM(G21:G22) | H23: =SUM(H21:H22) | I23: =SUM(I21:I22) | J23: =SUM(J21:J22) | K23: =SUM(K21:K22)
B25: Long-term Debt | D25: 600 | E25: 550 | F25: 500 | G25: 450 | H25: 400 | I25: 350 | J25: 300 | K25: 250
B26: Other Long-term Liabilities | D26: 80 | E26: 80 | F26: 80 | G26: 80 | H26: 80 | I26: 80 | J26: 80 | K26: 80
B27: Total Long-term Liabilities | D27: =SUM(D25:D26) | E27: =SUM(E25:E26) | F27: =SUM(F25:F26) | G27: =SUM(G25:G26) | H27: =SUM(H25:H26) | I27: =SUM(I25:I26) | J27: =SUM(J25:J26) | K27: =SUM(K25:K26)
B29: TOTAL LIABILITIES | D29: =D23+D27 | E29: =E23+E27 | F29: =F23+F27 | G29: =G23+G27 | H29: =H23+H27 | I29: =I23+I27 | J29: =J23+J27 | K29: =K23+K27
B31: EQUITY
B32: Common Stock | D32: 200 | E32: 200 | F32: 200 | G32: 200 | H32: 200 | I32: 200 | J32: 200 | K32: 200
B33: Retained Earnings | D33: 890 | E33: =D33+IS!E20 | F33: =E33+IS!F20 | G33: =F33+IS!G20 | H33: =G33+IS!H20 | I33: =H33+IS!I20 | J33: =I33+IS!J20 | K33: =J33+IS!K20
B34: TOTAL EQUITY | D34: =D32+D33 | E34: =E32+E33 | F34: =F32+F33 | G34: =G32+G33 | H34: =H32+H33 | I34: =I32+I33 | J34: =J32+J33 | K34: =K32+K33
B36: TOTAL LIABILITIES & EQUITY | D36: =D29+D34 | E36: =E29+E34 | F36: =F29+F34 | G36: =G29+G34 | H36: =H29+H34 | I36: =I29+I34 | J36: =J29+J34 | K36: =K29+K34
B38: Balance Check (should be 0) | D38: =D18-D36 | E38: =E18-E36 | F38: =F18-F36 | G38: =G18-G36 | H38: =H18-H36 | I38: =I18-I36 | J38: =J18-J36 | K38: =K18-K36

Sheet CF
D2: 2021A | E2: 2022A | F2: 2023A | G2: 2024E | H2: 2025E | I2: 2026E | J2: 2027E | K2: 2028E
B4: CASH FLOW STATEMENT ($M)
B6: OPERATING ACTIVITIES
B7: Net Income | D7: =IS!D20 | E7: =IS!E20 | F7: =IS!F20 | G7: =IS!G20 | H7: =IS!H20 | I7: =IS!I20 | J7: =IS!J20 | K7: =IS!K20
B8: D&A (add back) | D8: =-IS!D12 | E8: =-IS!E12 | F8: =-IS!F12 | G8: =-IS!G12 | H8: =-IS!H12 | I8: =-IS!I12 | J8: =-IS!J12 | K8: =-IS!K12
B9: Change in Working Capital | D9: -25 | E9: =-(BS!E8-BS!D8)-(BS!E9-BS!D9)+(BS!E21-BS!D21) | F9: =-(BS!F8-BS!E8)-(BS!F9-BS!E9)+(BS!F21-BS!E21) | G9: =-(BS!G8-BS!F8)-(BS!G9-BS!F9)+(BS!G21-BS!F21) | H9: =-(BS!H8-BS!G8)-(BS!H9-BS!G9)+(BS!H21-BS!G21) | I9: =-(BS!I8-BS!H8)-(BS!I9-BS!H9)+(BS!I21-BS!H21) | J9: =-(BS!J8-BS!I8)-(BS!J9-BS!I9)+(BS!J21-BS!I21) | K9: =-(BS!K8-BS!J8)-(BS!K9-BS!J9)+(BS!K21-BS!J21)
B11: Cash from Operations | D11: =D7+D8+D9 | E11: =E7+E8+E9 | F11: =F7+F8+F9 | G11: =G7+G8+G9 | H11: =H7+H8+H9 | I11: =I7+I8+I9 | J11: =J7+J8+J9 | K11: =K7+K8+K9
B13: INVESTING ACTIVITIES
B14: Capital Expenditures | D14: =-Revenue!D12*Assumptions!D23 | E14: =-Revenue!E12*Assumptions!E23 | F14: =-Revenue!F12*Assumptions!F23 | G14: =-Revenue!G12*Assumptions!G23 | H14: =-Revenue!H12*Assumptions!H23 | I14: =-Revenue!I12*Assumptions!I23 | J14: =-Revenue!J12*Assumptions!J23 | K14: =-Revenue!K12*Assumptions!K23
B15: Cash from Investing | D15: =D14 | E15: =E14 | F15: =F14 | G15: =G14 | H15: =H14 | I15: =I14 | J15: =J14 | K15: =K14
B17: FINANCING ACTIVITIES
B18: Debt Repayment | D18: 0 | E18: =BS!E25-BS!D25 | F18: =BS!F25-BS!E25 | G18: =BS!G25-BS!F25 | H18: =BS!H25-BS!G25 | I18: =BS!I25-BS!H25 | J18: =BS!J25-BS!I25 | K18: =BS!K25-BS!J25
B19: Dividends Paid | D19: 0 | E19: 0 | F19: 0 | G19: 0 | H19: 0 | I19: 0 | J19: 0 | K19: 0
B20: Cash from Financing | D20: =D18+D19 | E20: =E18+E19 | F20: =F18+F19 | G20: =G18+G19 | H20: =H18+H19 | I20: =I18+I19 | J20: =J18+J19 | K20: =K18+K19
B22: SUMMARY
B24: Beginning Cash | D24: 380 | E24: =D27 | F24: =E27 | G24: =F27 | H24: =G27 | I24: =H27 | J24: =I27 | K24: =J27
B25: Net Change in Cash | D25: =D11+D15+D20 | E25: =E11+E15+E20 | F25: =F11+F15+F20 | G25: =G11+G15+G20 | H25: =H11+H15+H20 | I25: =I11+I15+I20 | J25: =J11+J15+J20 | K25: =K11+K15+K20
B27: Ending Cash | D27: =D24+D25 | E27: =E24+E25 | F27: =F24+F25 | G27: =G24+G25 | H27: =H24+H25 | I27: =I24+I25 | J27: =J24+J25 | K27: =K24+K25
B28: Change in Cash (for BS) | D28: =D25 | E28: =E25 | F28: =F25 | G28: =G25 | H28: =H25 | I28: =I25 | J28: =J25 | K28: =K25

Sheet DCF
D2: 2024E | E2: 2025E | F2: 2026E | G2: 2027E | H2: 2028E | I2: Terminal
B4: DCF VALUATION ($M)
B6: KEY ASSUMPTIONS
B7: WACC | D7: 0.1
B8: Terminal Growth Rate | D8: 0.025
B11: FREE CASH FLOW
B12: EBIT | D12: =IS!G13 | E12: =IS!H13 | F12: =IS!I13 | G12: =IS!J13 | H12: =IS!K13
B13: Less: Taxes | D13: =-G12*Assumptions!G27 | E13: =-H12*Assumptions!H27 | F13: =-I12*Assumptions!I27 | G13: =-J12*Assumptions!J27 | H13: =-K12*Assumptions!K27
B14: EBIAT | D14: =D12+D13 | E14: =E12+E13 | F14: =F12+F13 | G14: =G12+G13 | H14: =H12+H13
B15: Plus: D&A | D15: =-IS!G12 | E15: =-IS!H12 | F15: =-IS!I12 | G15: =-IS!J12 | H15: =-IS!K12
B16: Less: CapEx | D16: =CF!G14 | E16: =CF!H14 | F16: =CF!I14 | G16: =CF!J14 | H16: =CF!K14
B17: Less: Change in NWC | D17: =CF!G9 | E17: =CF!H9 | F17: =CF!I9 | G17: =CF!J9 | H17: =CF!K9
B18: Unlevered Free Cash Flow | D18: =D14+D15+D16+D17 | E18: =E14+E15+E16+E17 | F18: =F14+F15+F16+F17 | G18: =G14+G15+G16+G17 | H18: =H14+H15+H16+H17 | I18: =H18*(1+$D$8)/($D$7-$D$8)
B20: DISCOUNTING
B21: Period | D21: 1 | E21: 2 | F21: 3 | G21: 4 | H21: 5 | I21: 5
B22: Discount Factor | D22: =1/(1+$D$7)^D21 | E22: =1/(1+$D$7)^E21 | F22: =1/(1+$D$7)^F21 | G22: =1/(1+$D$7)^G21 | H22: =1/(1+$D$7)^H21 | I22: =1/(1+$D$7)^I21
B23: PV of Cash Flow | D23: =D18*D22 | E23: =E18*E22 | F23: =F18*F22 | G23: =G18*G22 | H23: =H18*H22 | I23: =I18*I22
B26: VALUATION SUMMARY
B28: PV of Forecast Period FCF | D28: =SUM(D23:H23)
B29: PV of Terminal Value | D29: =I23
B30: Enterprise Value | D30: =D28+D29
B32: Less: Net Debt (2023) | D32: =BS!F25-BS!F7
B33: Equity Value | D33: =D30-D32
B35: Shares Outstanding (M) | D35: 150
B36: Implied Share Price | D36: =D33/D35
